<?xml version="1.0" encoding="UTF-8"?>

<databaseChangeLog
        xmlns="http://www.liquibase.org/xml/ns/dbchangelog"
        xmlns:xsi="http://www.w3.org/2001/XMLSchema-instance"
        xmlns:pro="http://www.liquibase.org/xml/ns/pro"
        xsi:schemaLocation="http://www.liquibase.org/xml/ns/dbchangelog http://www.liquibase.org/xml/ns/dbchangelog/dbchangelog-4.6.xsd
    http://www.liquibase.org/xml/ns/pro http://www.liquibase.org/xml/ns/pro/liquibase-pro-4.6.xsd ">

    <changeSet id="6" author="table_orders">
        <createTable tableName="orders">
            <column name="id" type="int">
                <constraints primaryKey="true"/>
            </column>
            <column name="date_created" type="date"/>
            <column name="status" type="varchar(255)"/>
        </createTable>
    </changeSet>

</databaseChangeLog>
